delayed_reactant_labeling/__init__.py
delayed_reactant_labeling/optimize.py
delayed_reactant_labeling/optimize_nelder_mead.py
delayed_reactant_labeling/predict.py
delayed_reactant_labeling/visualize.py
delayed_reactant_labeling-0.3.1.dist-info/LICENSE.txt
delayed_reactant_labeling-0.3.1.dist-info/METADATA
delayed_reactant_labeling-0.3.1.dist-info/WHEEL
delayed_reactant_labeling-0.3.1.dist-info/top_level.txt
delayed_reactant_labeling-0.3.1.dist-info/RECORD
