Metadata-Version: 2.1
Name: delayed-reactant-labeling
Version: 0.3.1
Summary: A toolbox for analysis of Delayed Reactant Labeling experiments.
Author-email: Martijn Dingemans <Martijn.Dingemans@ru.nl>, Matthijs Hellinghuizen <matthijs.hellinghuizen@ru.nl>
Classifier: Programming Language :: Python :: 3
Requires-Python: >=3.8
License-File: LICENSE.txt
Requires-Dist: numpy
Requires-Dist: scipy
Requires-Dist: matplotlib
Requires-Dist: scikit-learn
Requires-Dist: numba
Requires-Dist: tqdm
Requires-Dist: openpyxl
Requires-Dist: pandas
Requires-Dist: joblib
